units/__init__.py
units/units.py
units/utils.py
rhseung.units-0.3.dist-info/LICENSE
rhseung.units-0.3.dist-info/METADATA
rhseung.units-0.3.dist-info/WHEEL
rhseung.units-0.3.dist-info/top_level.txt
rhseung.units-0.3.dist-info/RECORD
