Metadata-Version: 2.1
Name: rhseung.units
Version: 0.3
Summary: A package for handling physics units.
Home-page: https://github.com/rhseung/units
Author: rhseung
Author-email: rhseungg@gmail.com
License: MIT
Keywords: units,physics,mathematics
Requires-Python: >=3.10
License-File: LICENSE
